llama_index/callbacks/literalai/__init__.py
llama_index/callbacks/literalai/base.py
llama_index_callbacks_literalai-1.3.1.dist-info/METADATA
llama_index_callbacks_literalai-1.3.1.dist-info/WHEEL
llama_index_callbacks_literalai-1.3.1.dist-info/licenses/LICENSE
llama_index_callbacks_literalai-1.3.1.dist-info/RECORD
