Metadata-Version: 2.4
Name: llama-index-callbacks-literalai
Version: 1.3.1
Summary: llama-index callbacks literalai integration
Author-email: Damien BUTY <damien@chainlit.io>
License-Expression: MIT
License-File: LICENSE
Requires-Python: <4.0,>=3.9
Requires-Dist: llama-index-core<0.15,>=0.13.0
